MANIFEST.in
README.md
requirements.txt
setup.py
cbot/__init__.py
cbot.egg-info/PKG-INFO
cbot.egg-info/SOURCES.txt
cbot.egg-info/dependency_links.txt
cbot.egg-info/requires.txt
cbot.egg-info/top_level.txt
cbot/adapters/__init__.py
cbot/adapters/baseadapters/__init__.py
cbot/adapters/baseadapters/adapter.py
cbot/adapters/baseadapters/base_adapter.py
cbot/adapters/baseadapters/multi_adapter.py
cbot/adapters/coreadapters/__init__.py
cbot/adapters/coreadapters/best_match.py
cbot/adapters/inputadapters/__init__.py
cbot/adapters/inputadapters/input_adapter.py
cbot/adapters/inputadapters/variable_input_type_adapter.py
cbot/adapters/noknowledgeadapters/__init__.py
cbot/adapters/noknowledgeadapters/no_knowledge_adapter.py
cbot/adapters/outputadapters/__init__.py
cbot/adapters/outputadapters/output_adapter.py
cbot/adapters/storageadapters/__init__.py
cbot/adapters/storageadapters/sql_storage.py
cbot/adapters/storageadapters/storage_adapter.py
cbot/api/__init__.py
cbot/api/turing/__init__.py
cbot/api/turing/turing.py
cbot/ext/__init__.py
cbot/ext/sqlalchemy_app/__init__.py
cbot/ext/sqlalchemy_app/models.py
cbot/ext/sqlalchemy_app/types.py
cbot/main/__init__.py
cbot/main/cbot.py
cbot/main/trainers.py
cbot/utils/__init__.py
cbot/utils/comparisons.py
cbot/utils/constants.py
cbot/utils/conversation.py
cbot/utils/preprocessors.py
cbot/utils/response_selection.py
cbot/utils/stopwords.py
cbot/utils/utils.py