Metadata-Version: 2.1
Name: cbot
Version: 0.1.4
Summary: A chinese chat bot
Home-page: https://github.com/wangyitao/cbot
Author: felix
Author-email: felix2@foxmail.com
Maintainer: felix
Maintainer-email: felix2@foxmail.com
License: MIT License
Platform: ubuntu
Platform: windows
Classifier: Development Status :: 4 - Beta
Classifier: Operating System :: OS Independent
Classifier: Intended Audience :: Developers
Classifier: License :: OSI Approved :: MIT License
Classifier: Programming Language :: Python
Classifier: Programming Language :: Python :: Implementation
Classifier: Programming Language :: Python :: 3.4
Classifier: Programming Language :: Python :: 3.5
Classifier: Programming Language :: Python :: 3.6
Classifier: Topic :: Software Development :: Libraries
